codraft/__init__.py
codraft/app.py
codraft/config.py
codraft/env.py
codraft/patch.py
codraft/core/__init__.py
codraft/core/computation/__init__.py
codraft/core/computation/fit.py
codraft/core/computation/image.py
codraft/core/computation/signal.py
codraft/core/gui/__init__.py
codraft/core/gui/actionhandler.py
codraft/core/gui/docks.py
codraft/core/gui/h5io.py
codraft/core/gui/main.py
codraft/core/gui/objectlist.py
codraft/core/gui/panel.py
codraft/core/gui/plotitemlist.py
codraft/core/gui/roieditor.py
codraft/core/gui/processor/__init__.py
codraft/core/gui/processor/base.py
codraft/core/gui/processor/image.py
codraft/core/gui/processor/signal.py
codraft/core/io/__init__.py
codraft/core/io/base.py
codraft/core/io/conv.py
codraft/core/io/image.py
codraft/core/io/signal.py
codraft/core/io/h5/__init__.py
codraft/core/io/h5/common.py
codraft/core/io/h5/generic.py
codraft/core/io/h5/mos07636.py
codraft/core/io/h5/utils.py
codraft/core/model/__init__.py
codraft/core/model/base.py
codraft/core/model/image.py
codraft/core/model/signal.py
codraft/data/CodraFT.chm
codraft/data/CodraFT_fr.chm
codraft/data/dependencies-py3-win32.txt
codraft/data/icons/chm.svg
codraft/data/icons/collapse.png
codraft/data/icons/collapse_selection.png
codraft/data/icons/delete.svg
codraft/data/icons/delete_all.svg
codraft/data/icons/dtype.png
codraft/data/icons/edit_shapes.svg
codraft/data/icons/expand.png
codraft/data/icons/expand_selection.png
codraft/data/icons/flip_horizontally.svg
codraft/data/icons/flip_vertically.svg
codraft/data/icons/h5browser.svg
codraft/data/icons/h5file.svg
codraft/data/icons/h5group.svg
codraft/data/icons/h5open.svg
codraft/data/icons/h5save.svg
codraft/data/icons/h5scalar.svg
codraft/data/icons/image.svg
codraft/data/icons/image_roi.svg
codraft/data/icons/image_roi_new.svg
codraft/data/icons/libre-gui-about.svg
codraft/data/icons/libre-gui-action-delete.svg
codraft/data/icons/libre-gui-binoculars.svg
codraft/data/icons/libre-gui-close.svg
CodraFT-2.2.1.dist-info/LICENSE
CodraFT-2.2.1.dist-info/Licence_CeCILL-B_V1-en.txt
CodraFT-2.2.1.dist-info/METADATA
CodraFT-2.2.1.dist-info/WHEEL
CodraFT-2.2.1.dist-info/entry_points.txt
CodraFT-2.2.1.dist-info/top_level.txt
CodraFT-2.2.1.dist-info/RECORD
