Metadata-Version: 2.1
Name: CodraFT
Version: 2.2.1
Summary: Signal and image processing software
Home-page: https://codra-ingenierie-informatique.github.io/CodraFT/
Author: Pierre Raybaut
Author-email: p.raybaut@codra.fr
License: BSD 3-Clause License
Classifier: Topic :: Scientific/Engineering
Classifier: Operating System :: MacOS
Classifier: Operating System :: Microsoft :: Windows
Classifier: Operating System :: OS Independent
Classifier: Operating System :: POSIX
Classifier: Operating System :: Unix
Classifier: Programming Language :: Python :: 3.7
Classifier: Programming Language :: Python :: 3.8
Classifier: Programming Language :: Python :: 3.9
Classifier: Programming Language :: Python :: 3.10
Requires-Python: <4,>=3.7
License-File: LICENSE
License-File: Licence_CeCILL-B_V1-en.txt
Requires-Dist: h5py (>=3.0)
Requires-Dist: NumPy (>=1.21)
Requires-Dist: SciPy (>=1.7)
Requires-Dist: scikit-image (>=0.18)
Requires-Dist: psutil (>=5.5)
Requires-Dist: guidata (>=2.3)
Requires-Dist: guiqwt (>=4.3)
Requires-Dist: QtPy (>=1.9)
Provides-Extra: dev
Requires-Dist: black ; extra == 'dev'
Requires-Dist: isort ; extra == 'dev'
Requires-Dist: pylint ; extra == 'dev'
Requires-Dist: Coverage ; extra == 'dev'
